sync_ram_16x4_mod.v


module sync_ram_16x4_mod(
    input        clk,
    input        we,
    input  [3:0] data,
    input  [3:0] addr,
    input        shift,
    input        weT,
    output [3:0] q
);

    // Variavel RAM (armazena dados)
    reg [3:0] ram[15:0];

    // Registra endereco de acesso
    reg [3:0] addr_reg;

    // Especifica conteudo inicial da RAM
    // a partir da leitura de arquivo usando $readmemb
    initial begin
    ram[0] = 4'b0001;
    end 

    always @ (posedge clk)
    begin
        // Escrita da memoria
        if (we)
            ram[addr] <= data;
        if (weT) begin
            if(ram[0] == 4'b0000) ram[0] = data;
            else if(ram[1] == 4'b0000) ram[1] = data;
            else if(ram[2] == 4'b0000) ram[2] = data;
            else if(ram[3] == 4'b0000) ram[3] = data;
            else if(ram[4] == 4'b0000) ram[4] = data;
            else if(ram[5] == 4'b0000) ram[5] = data;
            else if(ram[6] == 4'b0000) ram[6] = data;
            else if(ram[7] == 4'b0000) ram[7] = data;
            else if(ram[8] == 4'b0000) ram[8] = data;
            else if(ram[9] == 4'b0000) ram[9] = data;
            else if(ram[10] == 4'b0000) ram[10] = data;
            else if(ram[11] == 4'b0000) ram[11] = data;
            else if(ram[12] == 4'b0000) ram[12] = data;
            else if(ram[13] == 4'b0000) ram[13] = data;
            else if(ram[14] == 4'b0000) ram[14] = data;
            else if(ram[15] == 4'b0000) ram[15] = data;
        end
        if(shift) begin 
            ram[0] = ram[1];
            ram[1] = ram[2];
            ram[2] = ram[3];
            ram[3] = ram[4];
            ram[4] = ram[5];
            ram[5] = ram[6];
            ram[6] = ram[7];
            ram[7] = ram[8];
            ram[8] = ram[9];
            ram[9] = ram[10];
            ram[10] = ram[11];
            ram[11] = ram[12];
            ram[12] = ram[13];
            ram[13] = ram[14];
            ram[14] = ram[15];
            ram[15] = 0;
        end    

        addr_reg <= addr;
    end

    // Atribuicao continua retorna dado
    assign q = ram[addr_reg];

endmodule

tb_ram_mod.v
module tb_ram_mod;
reg clk;
reg we=0;
reg [3:0] data;
reg [3:0] addr;
reg shift=0;
reg weT=0;
wire [3:0]q;

sync_ram_16x4_mod duut (clk,we,data,addr,shift,weT,q);
initial clk=0;
always #2 clk = ~clk;

initial begin
    $dumpfile("tb_ram_mod.vcd");
    $dumpvars(0,tb_ram_mod);
     // Teste 1. Guardar 10 no endereço 2
      addr = 2;
      data = 10;
      #10;
      we = 1;
      #5
      we = 0;
      // Teste 2. guarda 8 no endereço 0, utilizando o weT
      data=8;
      #10;
      weT=1;
      #2;
      weT=0;
      // Teste 3. coloca 5 no endereço 1, utilizando o weT
      data=5;
      #10;
      weT=1;
      #2;
      weT=0;
      //Teste 4. Shift
      #2;
      shift=1;
      #2;
      shift=0;
      #10;
      
      $finish;
    end
endmodule

tb_ram_mod.vcd
$date
	Tue Mar 12 23:28:20 2024
$end
$version
	ModelSim Version 2020.1
$end
$timescale
	1ns
$end

$scope module tb_ram_mod $end
$var reg 1 ! clk $end
$var reg 1 " we $end
$var reg 4 # data [3:0] $end
$var reg 4 $ addr [3:0] $end
$var reg 1 % shift $end
$var reg 1 & weT $end
$var wire 1 ' q [3] $end
$var wire 1 ( q [2] $end
$var wire 1 ) q [1] $end
$var wire 1 * q [0] $end

$scope module duut $end
$var wire 1 + clk $end
$var wire 1 , we $end
$var wire 1 - data [3] $end
$var wire 1 . data [2] $end
$var wire 1 / data [1] $end
$var wire 1 0 data [0] $end
$var wire 1 1 addr [3] $end
$var wire 1 2 addr [2] $end
$var wire 1 3 addr [1] $end
$var wire 1 4 addr [0] $end
$var wire 1 5 shift $end
$var wire 1 6 weT $end
$var wire 1 ' q [3] $end
$var wire 1 ( q [2] $end
$var wire 1 ) q [1] $end
$var wire 1 * q [0] $end
$var reg 4 7 addr_reg [3:0] $end
$upscope $end
$upscope $end
$enddefinitions $end
#0
$dumpvars
0!
0"
b1010 #
b10 $
0%
0&
bx 7
x*
x)
x(
x'
06
05
04
13
02
01
00
1/
0.
1-
0,
0+
$end
#2
1!
1+
b10 7
0*
0)
0(
0'
#4
0!
0+
#6
1!
1+
#8
0!
0+
#10
1"
1!
1,
1+
1)
1'
#12
0!
0+
#14
1!
1+
#15
0"
b1000 #
0,
0/
#16
0!
0+
#18
1!
1+
#20
0!
0+
#22
1!
1+
#24
0!
0+
#25
1&
16
#26
1!
1+
#27
0&
b101 #
06
10
1.
0-
#28
0!
0+
#30
1!
1+
#32
0!
0+
#34
1!
1+
#36
0!
0+
#37
1&
16
#38
1!
1+
#39
0&
06
#40
0!
0+
#41
1%
15
#42
1!
1+
0)
0'
#43
0%
05
